matchcake/__init__.py
matchcake/base/__init__.py
matchcake/base/lookup_table.py
matchcake/circuits/__init__.py
matchcake/circuits/random_generator.py
matchcake/circuits/random_matchgate_circuits.py
matchcake/circuits/random_parametrize_circuit_generator.py
matchcake/circuits/random_sptm_circuits.py
matchcake/constants/__init__.py
matchcake/devices/__init__.py
matchcake/devices/device_utils.py
matchcake/devices/nif_device.py
matchcake/devices/contraction_strategies/__init__.py
matchcake/devices/contraction_strategies/contraction_container.py
matchcake/devices/contraction_strategies/contraction_strategy.py
matchcake/devices/contraction_strategies/forward_strategy.py
matchcake/devices/contraction_strategies/horizontal_strategy.py
matchcake/devices/contraction_strategies/neighbours_strategy.py
matchcake/devices/contraction_strategies/none_strategy.py
matchcake/devices/contraction_strategies/vertical_strategy.py
matchcake/devices/expval_strategies/__init__.py
matchcake/devices/expval_strategies/expval_from_probabilities.py
matchcake/devices/expval_strategies/expval_strategy.py
matchcake/devices/expval_strategies/terms_splitter.py
matchcake/devices/expval_strategies/clifford_expval/__init__.py
matchcake/devices/expval_strategies/clifford_expval/_pauli_map.py
matchcake/devices/expval_strategies/clifford_expval/clifford_expval_strategy.py
matchcake/devices/probability_strategies/__init__.py
matchcake/devices/probability_strategies/clifford_sum_strategy.py
matchcake/devices/probability_strategies/explicit_sum_strategy.py
matchcake/devices/probability_strategies/lookup_table_strategy.py
matchcake/devices/probability_strategies/probability_strategy.py
matchcake/devices/sampling_strategies/__init__.py
matchcake/devices/sampling_strategies/k_qubits_by_k_qubits_sampling.py
matchcake/devices/sampling_strategies/qubit_by_qubit_sampling.py
matchcake/devices/sampling_strategies/sampling_strategy.py
matchcake/devices/sampling_strategies/two_qubits_by_two_qubits_sampling.py
matchcake-0.2.0.dist-info/LICENSE
matchcake-0.2.0.dist-info/METADATA
matchcake-0.2.0.dist-info/WHEEL
matchcake-0.2.0.dist-info/top_level.txt
matchcake-0.2.0.dist-info/RECORD
