Metadata-Version: 2.1
Name: matchcake
Version: 0.2.0
Author-email: Jérémie Gince <gincejeremie@gmail.com>
License: Apache License
Project-URL: homepage, https://github.com/MatchCake/MatchCake
Project-URL: Documentation, https://github.com/MatchCake/MatchCake
Project-URL: Source, https://MatchCake.github.io/MatchCake
Classifier: Development Status :: 3 - Alpha
Classifier: Intended Audience :: Science/Research
Classifier: License :: OSI Approved :: Apache Software License
Classifier: Programming Language :: Python :: 3
Classifier: Programming Language :: Python :: 3.10
Classifier: Topic :: Scientific/Engineering
Classifier: Topic :: Scientific/Engineering :: Artificial Intelligence
Classifier: Topic :: Software Development :: Libraries :: Python Modules
Classifier: Operating System :: OS Independent
Requires-Python: >=3.10
License-File: LICENSE
Requires-Dist: numpy<3.0.0,>=1.23
Requires-Dist: setuptools>=65.5.1
Requires-Dist: scipy<=2,>=1.11.4
Requires-Dist: matplotlib>=3.8.0
Requires-Dist: networkx<4.0,>=3.1
Requires-Dist: pythonbasictools>=0.0.1a10
Requires-Dist: sympy<2.0,>=1.12
Requires-Dist: tqdm>=4.66.1
Requires-Dist: seaborn>=0.13.0
Requires-Dist: scikit-learn>=1.3.2
Requires-Dist: psutil>=5.9.6
Requires-Dist: torch<3.0.0,>=2.1.2
Requires-Dist: pylint>=3.1.0
Requires-Dist: pennylane<=0.41.1,>=0.39.0
Requires-Dist: pandas>=2.1.0
Requires-Dist: pennylane-lightning<=0.41.1,>=0.39.0
Requires-Dist: torchpfaffian>=0.0.0
Requires-Dist: opt-einsum>=3.4.0
Requires-Dist: importlib-metadata<9.0.0,>=8.7.0
Requires-Dist: stim>=1.15.0
Requires-Dist: autoray<=0.7.2
Provides-Extra: cpu
Requires-Dist: torch<3.0.0,>=2.1.2; extra == "cpu"
Requires-Dist: torchvision>=0.21.0; extra == "cpu"
Provides-Extra: cu128
Requires-Dist: torch<3.0.0,>=2.1.2; extra == "cu128"
Requires-Dist: torchvision>=0.21.0; extra == "cu128"
Provides-Extra: cu130
Requires-Dist: torch<3.0.0,>=2.1.2; extra == "cu130"
Requires-Dist: torchvision>=0.22.0; extra == "cu130"
